sentiml/__init__.py
sentiml/default_libraries.py
sentiml/inclusion.py
sentiml/protocols.py
sentiml/slugify.py
sentiml/stack_element.py
sentiml/stack_trace.py
sentiml/stacks.py
sentiml/trace_id.py
sentiml/track_class.py
sentiml/trackers.py
sentiml/tracking_type.py
sentiml-0.0.1.dist-info/METADATA
sentiml-0.0.1.dist-info/WHEEL
sentiml-0.0.1.dist-info/RECORD
