Metadata-Version: 2.1
Name: sentiml
Version: 0.0.1
Summary: Sentinel for ML Models
License: LGPL-3.0-or-later
Author: Lissa Hyacinth
Author-email: lissa@shareableai.com
Requires-Python: >=3.10,<3.11
Classifier: License :: OSI Approved :: GNU Lesser General Public License v3 or later (LGPLv3+)
Classifier: Programming Language :: Python :: 3
Classifier: Programming Language :: Python :: 3.10
Requires-Dist: weaver-json (>=0.0.2)
